shape_calculator/__init__.py
shape_calculator/arithops.py
shape_calculator/arithops_extended.py
shape_calculator/cli_shape.py
shape_calculator/shapes/__init__.py
shape_calculator/shapes/rectangle.py
shape_calculator/shapes/shape.py
shape_calculator/shapes/triangle.py
shape_calculator/version.py
shape_calculator-0.1.0.dist-info/LICENSE
shape_calculator-0.1.0.dist-info/METADATA
shape_calculator-0.1.0.dist-info/WHEEL
shape_calculator-0.1.0.dist-info/entry_points.txt
shape_calculator-0.1.0.dist-info/RECORD
