Metadata-Version: 2.1
Name: shape-calculator
Version: 0.1.0
Summary: Package for object-oriented programming, collaborative development, and generalized programming
Home-page: https://github.com/joonyeobjeon/practice-problem1
License: MIT
Author: Soohee Kim
Author-email: sssueing@gmail.com
Requires-Python: >=3.7
Classifier: License :: OSI Approved :: MIT License
Classifier: Programming Language :: Python :: 3
Classifier: Programming Language :: Python :: 3.7
Classifier: Programming Language :: Python :: 3.8
Classifier: Programming Language :: Python :: 3.9
Classifier: Programming Language :: Python :: 3.10
Classifier: Programming Language :: Python :: 3.11
Requires-Dist: click (>=8.1.3,<9.0.0)
Project-URL: Repository, https://github.com/joonyeobjeon/practice-problem1
